openg2p_g2pconnect_common_lib/__init__.py
openg2p_g2pconnect_common_lib/config.py
openg2p_g2pconnect_common_lib/jwt_signature_validator.py
openg2p_g2pconnect_common_lib/jwt_validation_helper.py
openg2p_g2pconnect_common_lib/errors/__init__.py
openg2p_g2pconnect_common_lib/errors/base_error.py
openg2p_g2pconnect_common_lib/errors/base_exception.py
openg2p_g2pconnect_common_lib/errors/error_codes.py
openg2p_g2pconnect_common_lib/errors/http_exceptions.py
openg2p_g2pconnect_common_lib/schemas/__init__.py
openg2p_g2pconnect_common_lib/schemas/async_schemas.py
openg2p_g2pconnect_common_lib/schemas/requests.py
openg2p_g2pconnect_common_lib/schemas/status_codes.py
openg2p_g2pconnect_common_lib/schemas/sync_schemas.py
openg2p_g2pconnect_common_lib-2.0.0.dist-info/METADATA
openg2p_g2pconnect_common_lib-2.0.0.dist-info/WHEEL
openg2p_g2pconnect_common_lib-2.0.0.dist-info/RECORD
